{
  "id": 49230,
  "guid": "7aa7f6ba-3b9c-552d-8193-531e366b8f88",
  "logo": "",
  "date": "2022-12-27T11:00:00+01:00",
  "start": "11:00",
  "duration": "00:40",
  "room": "Fireshonks-Stream",
  "slug": "jev22-49230-opening",
  "url": "https://pretalx.c3voc.de/fire-shonks-2022/talk/NNNAK3/",
  "title": "Opening",
  "subtitle": "",
  "track": "R3S",
  "type": "Talk",
  "language": "de",
  "abstract": "Veranstaltungsbeginn mit Einf\u00fchrung\r\n\r\nStream-Link: https://streaming.media.ccc.de/jev22/fireshonks",
  "description": "Vor den ersten Vortrag die Veranstaltung er\u00f6ffnen.",
  "recording_license": "",
  "do_not_record": false,
  "persons": [
    {
      "id": 972,
      "code": "WFVS9W",
      "public_name": "Fireshork",
      "biography": "Wie immer...",
      "answers": []
    }
  ],
  "links": [],
  "attachments": [],
  "room_id": "c62a781e-48a3-4546-bb5c-dee2080738f7",
  "origin": "pretalx.c3voc.de"
}