{
  "id": 49232,
  "guid": "d4c1c6c4-9f83-5ec8-80a1-5dd9011f4c12",
  "logo": "",
  "date": "2022-12-30T15:00:00+01:00",
  "start": "15:00",
  "duration": "00:45",
  "room": "xrelog22 - Stream",
  "slug": "xrelog-2022-49232-energie-daten",
  "url": "https://pretalx.c3voc.de/xrelog-2022/talk/WWKKFY/",
  "title": "Energie & Daten",
  "subtitle": "",
  "track": "Activism",
  "type": "Diskussions Panel (zzgl. Q&A)",
  "language": "de",
  "abstract": "Energie & Daten",
  "description": "Ein Panel-Slot f\u00fcr und mit Bits und B\u00e4ume",
  "recording_license": "",
  "do_not_record": false,
  "persons": [
    {
      "id": 3351,
      "code": "SEVDXT",
      "public_name": "Matthias",
      "biography": null,
      "answers": []
    }
  ],
  "links": [],
  "attachments": [],
  "room_id": "ad28953f-122e-4293-836d-860320183a1c",
  "origin": "pretalx.c3voc.de"
}