{
  "id": 49291,
  "guid": "ec47ccd5-d68d-5ba3-948a-a8ed5056a2d8",
  "logo": "",
  "date": "2022-12-29T15:00:00+01:00",
  "start": "15:00",
  "duration": "00:30",
  "room": "Bierschoine",
  "slug": "hacking-in-hell-2022-49291-berwacht-mehr-insekten-",
  "url": "https://pretalx.c3voc.de/hacking-in-hell-2022/talk/B8CYZU/",
  "title": "\u00dcberwacht mehr Insekten!",
  "subtitle": "",
  "track": "Hellarious",
  "type": "Talk",
  "language": "de",
  "abstract": "Entomolog:innen sind eine aussterbende Spezies mit einem krassen F\u00e4higkeitspektrum. Die zur\u00fcckgehenden Ergebnisse der Feldarbeit versucht man mangels Expert:innennachwuchs seit einiger Zeit durch die Entwicklung verschiedener Citizen Science-Projekten zu kompensieren. Doch warum ist ein kontinuierliches Insekten-Monitoring eigentlich so wichtig? - Nicht nur f\u00fcr die Tierchen selber, sondern letztendlich auch f\u00fcr uns und die uns umgebenden \u00d6kosysteme? Ein kleiner Einblick sowie unkomplizierte Handelsoptionen werden in diesem Talk, v. A. am Beispiel der Wildbienen, vermittelt.",
  "description": "Nach einem gem\u00fctlichen Input zur \u00f6kologischen Situation der Wildbienen (v. A. in Europa) und warum uns diese interessieren sollte, werden ein paar verschiedene Projekte/Ans\u00e4tze vorgestellt, welche M\u00f6glichkeiten zur Verbesserung der Situation versucht werden und wie man sich einbringen kann, bevor wir in den offenen Austausch einsteigen.",
  "recording_license": "",
  "do_not_record": false,
  "persons": [
    {
      "id": 3399,
      "code": "9NFMXH",
      "public_name": "curtisanne",
      "biography": "\u2026von fast allem ein bisschen. Schlie\u00dflich will ich wissen, was die Welt im Innersten zusammenh\u00e4lt.",
      "answers": []
    }
  ],
  "links": [],
  "attachments": [],
  "room_id": "0ce1f1b3-35c6-48ee-b3db-1c54e85f36b4",
  "origin": "pretalx.c3voc.de"
}